{
    "availableLanguageIds": [
        "en_US"
    ],
    "defaultLanguageId": "en_US",
    "fields": [
        {
            "label": {
                "en_US": "Image"
            },
            "predefinedValue": {
                "en_US": ""
            },
            "style": {
                "en_US": ""
            },
            "tip": {
                "en_US": ""
            },
            "dataType": "document-library",
            "fieldNamespace": "ddm",
            "indexType": "",
            "localizable": false,
            "name": "Image",
            "readOnly": false,
            "repeatable": true,
            "required": true,
            "showLabel": true,
            "type": "ddm-documentlibrary",
            "nestedFields": [
                {
                    "label": {
                        "en_US": "Alt"
                    },
                    "predefinedValue": {
                        "en_US": ""
                    },
                    "style": {
                        "en_US": ""
                    },
                    "tip": {
                        "en_US": ""
                    },
                    "dataType": "string",
                    "indexType": "text",
                    "localizable": true,
                    "name": "alt",
                    "readOnly": false,
                    "repeatable": false,
                    "required": false,
                    "showLabel": true,
                    "type": "textarea"
                }
            ]
        }
    ]
}